omni_nli/__init__.py
omni_nli/__main__.py
omni_nli/api_models.py
omni_nli/errors.py
omni_nli/event_store.py
omni_nli/mcp.py
omni_nli/py.typed
omni_nli/rest.py
omni_nli/settings.py
omni_nli/tools.py
omni_nli/providers/__init__.py
omni_nli/providers/base.py
omni_nli/providers/factory.py
omni_nli/providers/huggingface.py
omni_nli/providers/ollama.py
omni_nli/providers/openrouter.py
omni_nli-0.1.0.dist-info/METADATA
omni_nli-0.1.0.dist-info/WHEEL
omni_nli-0.1.0.dist-info/entry_points.txt
omni_nli-0.1.0.dist-info/licenses/LICENSE
omni_nli-0.1.0.dist-info/RECORD
