Metadata-Version: 2.4
Name: omni-nli
Version: 0.1.0
Summary: A multi-interface (REST and MCP) server for natural language inference
Project-URL: Repository, https://github.com/CogitatorTech/omni-nli
Project-URL: Documentation, https://cogitatortech.github.io/omni-nli/
Author-email: Hassan Abedi <hassan.abedi.t+omninli@gmail.com>
Maintainer-email: Hassan Abedi <hassan.abedi.t+omninli@gmail.com>
License: MIT
License-File: LICENSE
Keywords: contradiction,entailment,huggingface,llm,mcp,microservice,natural-language-inference,nli,ollama,openrouter,rest-api
Classifier: Development Status :: 4 - Beta
Classifier: Intended Audience :: Developers
Classifier: License :: OSI Approved :: MIT License
Classifier: Operating System :: OS Independent
Classifier: Programming Language :: Python :: 3
Classifier: Programming Language :: Python :: 3.10
Classifier: Programming Language :: Python :: 3.11
Classifier: Programming Language :: Python :: 3.12
Classifier: Programming Language :: Python :: 3.13
Classifier: Programming Language :: Python :: 3.14
Classifier: Topic :: Internet :: WWW/HTTP :: WSGI :: Application
Classifier: Topic :: Scientific/Engineering :: Artificial Intelligence
Classifier: Topic :: Software Development :: Libraries :: Python Modules
Classifier: Topic :: Text Processing :: Linguistic
Classifier: Topic :: Utilities
Requires-Python: <4.0,>=3.10
Requires-Dist: async-lru<3.0.0,>=2.0.4
Requires-Dist: click<9.0.0,>=8.2.1
Requires-Dist: gunicorn<24.0.0,>=23.0.0
Requires-Dist: httpx<0.29.0,>=0.28.1
Requires-Dist: json-repair<1.0.0,>=0.55.1
Requires-Dist: mcp[cli]<2.0.0,>=1.12.3
Requires-Dist: ollama<1.0.0,>=0.4.0
Requires-Dist: openai<2.0.0,>=1.60.0
Requires-Dist: pydantic-settings<3.0.0,>=2.10.1
Requires-Dist: pydantic<3.0.0,>=2.12.0
Requires-Dist: python-dotenv<2.0.0,>=1.1.0
Requires-Dist: python-json-logger<4.0.0,>=3.3.0
Requires-Dist: spectree[starlette]<3.0.0,>=2.0.1
Requires-Dist: tiktoken<1.0.0,>=0.8.0
Provides-Extra: dev
Requires-Dist: accelerate<2.0.0,>=1.12.0; extra == 'dev'
Requires-Dist: asgi-lifespan[dev]<3.0.0,>=2.1.0; extra == 'dev'
Requires-Dist: huggingface-hub<1.0.0,>=0.27.0; extra == 'dev'
Requires-Dist: hypothesis<7.0.0,>=6.150.2; extra == 'dev'
Requires-Dist: mkdocs-material<10.0.0,>=9.6.12; extra == 'dev'
Requires-Dist: mkdocs<2.0.0,>=1.6.1; extra == 'dev'
Requires-Dist: mkdocstrings-python<2.0.0,>=1.16.10; extra == 'dev'
Requires-Dist: mypy<2.0.0,>=1.11.1; extra == 'dev'
Requires-Dist: pre-commit<5.0.0,>=4.2.0; extra == 'dev'
Requires-Dist: pytest-asyncio<2.0.0,>=1.1.0; extra == 'dev'
Requires-Dist: pytest-cov<8.0.0,>=6.0.0; extra == 'dev'
Requires-Dist: pytest-mock<4.0.0,>=3.14.0; extra == 'dev'
Requires-Dist: pytest<10.0.0,>=8.0.1; extra == 'dev'
Requires-Dist: pyyaml<7.0.0,>=6.0.1; extra == 'dev'
Requires-Dist: ruff<1.0.0,>=0.9.3; extra == 'dev'
Requires-Dist: rundoc<0.3.0,>=0.2.3; extra == 'dev'
Requires-Dist: torch<3.0.0,>=2.0.0; extra == 'dev'
Requires-Dist: transformers<5.0.0,>=4.57.6; extra == 'dev'
Provides-Extra: huggingface
Requires-Dist: accelerate<2.0.0,>=1.12.0; extra == 'huggingface'
Requires-Dist: huggingface-hub<1.0.0,>=0.27.0; extra == 'huggingface'
Requires-Dist: torch<3.0.0,>=2.0.0; extra == 'huggingface'
Requires-Dist: transformers<5.0.0,>=4.57.6; extra == 'huggingface'
